{"event":{"id":86450,"tournament_id":21057,"tournament":"BCAF-WEST Y-12 and Y-14 Mixed Foil-YOUTH CUP #2","full_name":"Y12 Mixed Foil","weapon":"Foil","gender":"Mixed","age_limit":"Y12","rating_limit":"Open","rating":"","rating_prediction":"NR","entries":0,"prereg_count":17,"is_team":false,"description":"","close_of_reg":"2013-04-07T10:00:00-04:00","fee":"0.00","preregs":[{"id":826045,"competitor_id":83371,"rating":"U","club":{"id":157,"name":"Bucks County Academy of Fencing","initials":"BCAF"},"competitor":{"id":83371,"usfa_id":"100137939","cff_id":"","fie_id":"","first_name":"Jacob","last_name":"Sjostedt","gender":"M","birthyear":2002}},{"id":833692,"competitor_id":96441,"rating":"U","club":{"id":157,"name":"Bucks County Academy of Fencing","initials":"BCAF"},"competitor":{"id":96441,"usfa_id":"100153960","cff_id":"","fie_id":"","first_name":"Michael","last_name":"Jung","gender":"M","birthyear":2001}},{"id":844376,"competitor_id":71227,"rating":"U","club":{"id":135,"name":"Fencing Academy of Philadelphia","initials":"FAP"},"competitor":{"id":71227,"usfa_id":"100131623","cff_id":"","fie_id":"","first_name":"Lydia","last_name":"Halter","gender":"F","birthyear":2000}},{"id":860697,"competitor_id":92751,"rating":"U","club":{"id":483,"name":"Baltimore Fencing Center","initials":"BFC"},"competitor":{"id":92751,"usfa_id":"100148274","cff_id":"","fie_id":"","first_name":"Laurence","last_name":"Crandon","gender":"M","birthyear":2000}},{"id":862571,"competitor_id":87702,"rating":"U","club":{"id":1100,"name":"Chesapeake Fencing Club","initials":"CHESAPEAKE"},"competitor":{"id":87702,"usfa_id":"100140405","cff_id":"","fie_id":"","first_name":"Paul","last_name":"DiVenti","gender":"M","birthyear":2000}},{"id":863106,"competitor_id":99519,"rating":"U","club":{"id":157,"name":"Bucks County Academy of Fencing","initials":"BCAF"},"competitor":{"id":99519,"usfa_id":"","cff_id":"","fie_id":"","first_name":"Sam","last_name":"Clayton","gender":"M","birthyear":2000}},{"id":864479,"competitor_id":82881,"rating":"U","club":{"id":4565,"name":"Liberty Fencing Club LLC","initials":"LIBERTY FC"},"competitor":{"id":82881,"usfa_id":"100137240","cff_id":"","fie_id":"","first_name":"Christopher","last_name":"Davis","gender":"M","birthyear":2003}},{"id":864716,"competitor_id":81966,"rating":"U","club":{"id":3643,"name":"Fencing Academy of Philadelphia-West","initials":"FAP-WEST"},"competitor":{"id":81966,"usfa_id":"100137102","cff_id":"","fie_id":"","first_name":"Tristan","last_name":"Szapary","gender":"M","birthyear":2001}},{"id":865728,"competitor_id":90824,"rating":"U","club":{"id":157,"name":"Bucks County Academy of Fencing","initials":"BCAF"},"competitor":{"id":90824,"usfa_id":"100144979","cff_id":"","fie_id":"","first_name":"Brent","last_name":"Khusid","gender":"M","birthyear":2000}},{"id":867132,"competitor_id":60816,"rating":"U","club":{"id":157,"name":"Bucks County Academy of Fencing","initials":"BCAF"},"competitor":{"id":60816,"usfa_id":"100126183","cff_id":"","fie_id":"","first_name":"Myles","last_name":"Bear","gender":"M","birthyear":2000}},{"id":867363,"competitor_id":87009,"rating":"U","club":{"id":157,"name":"Bucks County Academy of Fencing","initials":"BCAF"},"competitor":{"id":87009,"usfa_id":"100139806","cff_id":"","fie_id":"","first_name":"Skylar","last_name":"Harfeld","gender":"F","birthyear":2000}},{"id":868758,"competitor_id":78670,"rating":"U","club":{"id":1699,"name":"Rockville Fencing Academy","initials":"RFA"},"competitor":{"id":78670,"usfa_id":"100138462","cff_id":"","fie_id":"","first_name":"Allison C.","last_name":"Hu","gender":"F","birthyear":2002}},{"id":868874,"competitor_id":88430,"rating":"U","club":{"id":157,"name":"Bucks County Academy of Fencing","initials":"BCAF"},"competitor":{"id":88430,"usfa_id":"","cff_id":"","fie_id":"","first_name":"Daniel","last_name":"Shulga","gender":"M","birthyear":2000}},{"id":869282,"competitor_id":82387,"rating":"U","club":{"id":3643,"name":"Fencing Academy of Philadelphia-West","initials":"FAP-WEST"},"competitor":{"id":82387,"usfa_id":"100137285","cff_id":"","fie_id":"","first_name":"Ian","last_name":"Adler","gender":"M","birthyear":2000}},{"id":870798,"competitor_id":77362,"rating":"U","club":{"id":279,"name":"Fencing Academy of South Jersey","initials":"FASJ"},"competitor":{"id":77362,"usfa_id":"100132065","cff_id":"","fie_id":"","first_name":"Emilio","last_name":"Obregon","gender":"M","birthyear":2001}},{"id":870799,"competitor_id":90728,"rating":"U","club":{"id":279,"name":"Fencing Academy of South Jersey","initials":"FASJ"},"competitor":{"id":90728,"usfa_id":"100141437","cff_id":"","fie_id":"","first_name":"Enrique","last_name":"Obregon","gender":"M","birthyear":2001}},{"id":870947,"competitor_id":91518,"rating":"U","club":{"id":135,"name":"Fencing Academy of Philadelphia","initials":"FAP"},"competitor":{"id":91518,"usfa_id":"100140018","cff_id":"","fie_id":"","first_name":"Calvin ","last_name":"Wang","gender":"M","birthyear":2001}}]}}